setup.py
transcoptract/__init__.py
transcoptract/settings.py
transcoptract/transcoptract.py
transcoptract.egg-info/PKG-INFO
transcoptract.egg-info/SOURCES.txt
transcoptract.egg-info/dependency_links.txt
transcoptract.egg-info/entry_points.txt
transcoptract.egg-info/requires.txt
transcoptract.egg-info/top_level.txt