Metadata-Version: 1.0
Name: transcoptract
Version: 1.05
Summary: Transmission Copy Extract Script
Home-page: UNKNOWN
Author: UNKNOWN
Author-email: UNKNOWN
License: UNKNOWN
Platform: UNKNOWN
